README.rst
setup.py
botify/__init__.py
botify/botify.py
botify/utils.py
botify.egg-info/PKG-INFO
botify.egg-info/SOURCES.txt
botify.egg-info/dependency_links.txt
botify.egg-info/top_level.txt