Metadata-Version: 1.1
Name: botify
Version: 0.1.3
Summary: Natural Language based Commands Processing Framework
Home-page: https://github.com/pri22296/botify
Author: Priyam Singh
Author-email: priyamsingh.22296@gmail.com
License: MIT
Download-URL: https://github.com/pri22296/botify/tarball/0.1.3
Platform: UNKNOWN
Classifier: Development Status :: 3 - Alpha
Classifier: Intended Audience :: Developers
Classifier: License :: OSI Approved :: MIT License
Classifier: Programming Language :: Python
Classifier: Programming Language :: Python :: 3.5
